setup.py
prettysettings/__init__.py
prettysettings/settings.py
prettysettings.egg-info/PKG-INFO
prettysettings.egg-info/SOURCES.txt
prettysettings.egg-info/dependency_links.txt
prettysettings.egg-info/requires.txt
prettysettings.egg-info/top_level.txt
tests/__init__.py
tests/prettysettings_test.py