Metadata-Version: 1.0
Name: prettysettings
Version: 1.3.3
Summary: This package provides a minimal class for pretty settings management.
Home-page: https://github.com/iottly/prettysettings
Author: Stefano Terna
Author-email: stefano.terna@tomorrowdata.io
License: Apache License, Version 2.0
Keywords: prettysettings settings json environment variables
Platform: UNKNOWN
